usb_resetter/__init__.py
usb_resetter/usb_resetter.py
usb_resetter-1.3.0.dist-info/LICENSE
usb_resetter-1.3.0.dist-info/METADATA
usb_resetter-1.3.0.dist-info/WHEEL
usb_resetter-1.3.0.dist-info/entry_points.txt
usb_resetter-1.3.0.dist-info/top_level.txt
usb_resetter-1.3.0.dist-info/RECORD
